examples/__init__.py
examples/bip32_keypair.py
examples/examples_utils.py
examples/transaction_aggregate.py
examples/transaction_multisig.py
examples/transaction_sign.py
examples/descriptors/__init__.py
examples/descriptors/nem_importance_transfer.py
examples/descriptors/nem_transfer.py
examples/descriptors/symbol_alias.py
examples/descriptors/symbol_key_link.py
examples/descriptors/symbol_lock.py
examples/descriptors/symbol_metadata.py
examples/descriptors/symbol_mosaic.py
examples/descriptors/symbol_namespace.py
examples/descriptors/symbol_restriction_account.py
examples/descriptors/symbol_restriction_mosaic.py
examples/descriptors/symbol_transfer.py
generator/AbstractImplMap.py
generator/AbstractTypeFormatter.py
generator/EnumTypeFormatter.py
generator/FactoryFormatter.py
generator/PodTypeFormatter.py
generator/StructTypeFormatter.py
generator/TypeFormatter.py
generator/__init__.py
generator/__main__.py
generator/format.py
generator/printers.py
generator/type_objects.py
symbolchain/__init__.py
symbolchain/core/AccountDescriptorRepository.py
symbolchain/core/ArrayHelpers.py
symbolchain/core/BaseValue.py
symbolchain/core/Bip32.py
symbolchain/core/BlockchainSettings.py
symbolchain/core/BufferReader.py
symbolchain/core/BufferWriter.py
symbolchain/core/ByteArray.py
symbolchain/core/CodeWordsEncoder.py
symbolchain/core/CryptoTypes.py
symbolchain/core/DiceMnemonicGenerator.py
symbolchain/core/Network.py
symbolchain/core/NetworkTimestamp.py
symbolchain/core/NodeDescriptorRepository.py
symbolchain/core/Ordered.py
symbolchain/core/PrivateKeyStorage.py
symbolchain/core/QrSignatureStorage.py
symbolchain/core/QrStorage.py
symbolchain/core/TransactionDescriptorProcessor.py
symbolchain/core/__init__.py
symbolchain/core/facade/BatchOperations.py
symbolchain/core/facade/NemFacade.py
symbolchain/core/facade/SymbolFacade.py
symbolchain/core/facade/__init__.py
symbolchain/core/nem/ImportanceTransferTransaction.py
symbolchain/core/nem/KeyPair.py
symbolchain/core/nem/Network.py
symbol_sdk_core_python-3.0.1.dist-info/METADATA
symbol_sdk_core_python-3.0.1.dist-info/WHEEL
symbol_sdk_core_python-3.0.1.dist-info/top_level.txt
symbol_sdk_core_python-3.0.1.dist-info/RECORD
