Metadata-Version: 2.1
Name: symbol-sdk-core-python
Version: 3.0.1
Summary: Symbol SDK Core
Home-page: https://github.com/symbol/sdk-python
Author: Symbol Contributors
Author-email: contributors@symbol.dev
License: MIT
Keywords: symbol,sdk,sdk-core,Symbol SDK core
Platform: UNKNOWN
Classifier: Programming Language :: Python :: 3.7
Requires-Dist: Pillow (==8.4.0)
Requires-Dist: PyYAML (==5.4.1)
Requires-Dist: cryptography (==3.4.6)
Requires-Dist: mnemonic (==0.20)
Requires-Dist: pysha3 (==1.0.2)
Requires-Dist: pyzbar (==0.1.8)
Requires-Dist: qrcode (==7.3.1)
